Metadata-Version: 2.2
Name: spendo-pynamodb
Version: 6.0.2.1
Summary: A Pythonic Interface to DynamoDB (fork with flag to return conflict record)
Home-page: http://jlafon.io/pynamodb.html
Author: Jharrod LaFon
Author-email: jlafon@eyesopen.com
License: MIT
Project-URL: Source, https://github.com/pynamodb/PynamoDB
Keywords: python dynamodb amazon
Classifier: Development Status :: 5 - Production/Stable
Classifier: Intended Audience :: Developers
Classifier: Programming Language :: Python
Classifier: Operating System :: OS Independent
Classifier: Programming Language :: Python :: 3.7
Classifier: Programming Language :: Python :: 3.8
Classifier: Programming Language :: Python :: 3.9
Classifier: Programming Language :: Python :: 3.10
Classifier: Programming Language :: Python :: 3.11
Classifier: Programming Language :: Python :: 3.12
Classifier: License :: OSI Approved :: MIT License
Requires-Python: >=3.7
License-File: LICENSE
Requires-Dist: botocore>=1.12.54
Requires-Dist: typing-extensions>=4; python_version < "3.11"
Provides-Extra: signals
Requires-Dist: blinker<2.0,>=1.3; extra == "signals"
Dynamic: author
Dynamic: author-email
Dynamic: classifier
Dynamic: description
Dynamic: description-content-type
Dynamic: home-page
Dynamic: keywords
Dynamic: license
Dynamic: project-url
Dynamic: provides-extra
Dynamic: requires-dist
Dynamic: requires-python
Dynamic: summary
